prometheus_aioexporter/__init__.py
prometheus_aioexporter/_log.py
prometheus_aioexporter/_metric.py
prometheus_aioexporter/_script.py
prometheus_aioexporter/_web.py
prometheus_aioexporter/py.typed
prometheus_aioexporter/sample.py
prometheus_aioexporter-3.1.0.dist-info/licenses/LICENSE.txt
prometheus_aioexporter-3.1.0.dist-info/METADATA
prometheus_aioexporter-3.1.0.dist-info/WHEEL
prometheus_aioexporter-3.1.0.dist-info/entry_points.txt
prometheus_aioexporter-3.1.0.dist-info/top_level.txt
prometheus_aioexporter-3.1.0.dist-info/RECORD
