Metadata-Version: 2.4
Name: prometheus-aioexporter
Version: 3.1.0
Summary: Asyncio library for creating Prometheus exporters
Author-email: Alberto Donato <alberto.donato@gmail.com>
Maintainer-email: Alberto Donato <alberto.donato@gmail.com>
License:                    GNU LESSER GENERAL PUBLIC LICENSE
Project-URL: changelog, https://github.com/albertodonato/prometheus-aioexporter/blob/main/CHANGES.rst
Project-URL: homepage, https://github.com/albertodonato/prometheus-aioexporter
Project-URL: repository, https://github.com/albertodonato/prometheus-aioexporter
Keywords: exporter,library,prometheus
Classifier: Development Status :: 4 - Beta
Classifier: Intended Audience :: Developers
Classifier: Intended Audience :: System Administrators
Classifier: License :: OSI Approved :: GNU Lesser General Public License v3 or later (LGPLv3+)
Classifier: Programming Language :: Python :: 3 :: Only
Classifier: Programming Language :: Python :: 3.11
Classifier: Programming Language :: Python :: 3.12
Classifier: Programming Language :: Python :: 3.13
Classifier: Topic :: Software Development :: Libraries
Classifier: Topic :: Software Development :: Libraries :: Python Modules
Classifier: Topic :: Utilities
Requires-Python: >=3.11
License-File: LICENSE.txt
Requires-Dist: aiohttp>=3
Requires-Dist: click>=8.2
Requires-Dist: prometheus-client>=0.4
Requires-Dist: python-dotenv
Requires-Dist: structlog
Provides-Extra: testing
Requires-Dist: pytest; extra == "testing"
Requires-Dist: pytest-aiohttp; extra == "testing"
Requires-Dist: pytest-asyncio; extra == "testing"
Requires-Dist: pytest-mock; extra == "testing"
Requires-Dist: pytest-structlog; extra == "testing"
Requires-Dist: trustme; extra == "testing"
Dynamic: license-file
